{
  "lexicon": 1,
  "id": "net.openfederation.community.deleteRole",
  "revision": 1,
  "description": "Delete a community role. Fails if any members are assigned to it.",
  "defs": {
    "main": {
      "type": "procedure",
      "input": {
        "encoding": "application/json",
        "schema": {
          "type": "object",
          "properties": {
            "communityDid": {
              "type": "string"
            },
            "rkey": {
              "type": "string"
            }
          },
          "required": [
            "communityDid",
            "rkey"
          ]
        }
      },
      "output": {
        "encoding": "application/json",
        "schema": {
          "type": "object",
          "properties": {
            "success": {
              "type": "boolean"
            }
          },
          "required": [
            "success"
          ]
        }
      },
      "errors": [
        {
          "name": "RoleNotFound",
          "description": "No role found with the given rkey."
        },
        {
          "name": "RoleInUse",
          "description": "Cannot delete a role that has members assigned."
        }
      ]
    }
  }
}
